tests/test_cli.py
tests/test_file_downloader.py
tests/test_parallel_url_fetcher.py
tests/test_progress_bar.py
tests/test_uqload.py
tests/test_utils.py
uqload_dl/__init__.py
uqload_dl/cli.py
uqload_dl/exceptions.py
uqload_dl/file_downloader.py
uqload_dl/parallel_url_fetcher.py
uqload_dl/progress_bar.py
uqload_dl/uqload.py
uqload_dl/utils.py
uqload_dl/version.py
uqload_dl-2.0.0.dist-info/licenses/LICENSE
uqload_dl-2.0.0.dist-info/METADATA
uqload_dl-2.0.0.dist-info/WHEEL
uqload_dl-2.0.0.dist-info/entry_points.txt
uqload_dl-2.0.0.dist-info/top_level.txt
uqload_dl-2.0.0.dist-info/RECORD
