Metadata-Version: 2.4
Name: uqload-dl
Version: 2.0.0
Summary: Download any video from the Uqload site
Author-email: Joel Flores <joelhernandez2982@gmail.com>
License:                     GNU GENERAL PUBLIC LICENSE
Project-URL: Homepage, https://github.com/JoelFH23/uqload-downloader-python
Project-URL: Source, https://github.com/JoelFH23/uqload-downloader-python
Keywords: video,uqload,downloader,streaming,python
Classifier: Programming Language :: Python :: 3
Classifier: License :: OSI Approved :: GNU General Public License v3 (GPLv3)
Classifier: Operating System :: OS Independent
Classifier: Topic :: Multimedia :: Video
Requires-Python: >=3.9
License-File: LICENSE
Provides-Extra: dev
Requires-Dist: pytest; extra == "dev"
Requires-Dist: build; extra == "dev"
Dynamic: license-file
